README.rst
setup.cfg
setup.py
mailjet/__init__.py
mailjet/api.py
mailjet/conf.py
mailjet/connection.py
mailjet/default_settings.py
mailjet/settings.py
mailjet.egg-info/PKG-INFO
mailjet.egg-info/SOURCES.txt
mailjet.egg-info/dependency_links.txt
mailjet.egg-info/top_level.txt
mailjet/contrib/__init__.py
mailjet/contrib/django_mailjet/__init__.py
mailjet/contrib/django_mailjet/forms.py
mailjet/contrib/django_mailjet/models.py
mailjet/contrib/django_mailjet/tests.py
mailjet/contrib/django_mailjet/urls.py
mailjet/contrib/django_mailjet/views.py
tests/__init__.py
tests/manage.py
tests/settings.py
tests/urls.py
tests/wsgi.py