Metadata-Version: 1.1
Name: mailjet
Version: 1.4.0
Summary: mailjet is a django app to implement the mailjet REST API
Home-page: https://github.com/WoLpH/mailjet
Author: Rick van Hattem
Author-email: Rick.van.Hattem@Fawo.nl
License: BSD
Platform: UNKNOWN
Classifier: License :: OSI Approved :: BSD License
